{
  "$schema": "https://developer.microsoft.com/json-schemas/sp/v2/column-formatting.schema.json",
  "elmType": "div",
  "style": {
    "display": "=if(@currentField,'flex','none')",
    "margin": "5px 0 5px 0"
  },
  "children": [
    {
      "elmType": "div",
      "style": {
        "display": "flex",
        "flex-direction": "column",
        "width": "39px",
        "height": "49px",
        "border-radius": "8px",
        "border": "3px solid",
        "justify-content": "flex-start",
        "background-color": "white",
        "border-color": "=if(@currentField>@now, '#107c10', if(toDateString(@currentField)==toDateString(@now), '#c43b33', 'gray'))",
        "box-shadow": "0 1px 3px rgba(0,0,0,0.12), 0 4px 6px rgba(0,0,0,0.08)"
      },
      "children": [
        {
          "elmType": "div",
          "txtContent": "=substring('JANFEBMARAPRMAYJUNJULAUGSEPOCTNOVDEC', getMonth(@currentField)*3, getMonth(@currentField)*3+3)",
          "style": {
            "display": "flex",
            "flex": "0 0 40%",
            "align-items": "center",
            "justify-content": "center",
            "letter-spacing": "1px",
            "font-weight": "bold",
            "background-color": "=if(@currentField>@now, '#107c10', if(toDateString(@currentField)==toDateString(@now), '#c43b33', 'gray'))",
            "color": "white"
          }
        },
        {
          "elmType": "div",
          "txtContent": "=getDate(@currentField)",
          "style": {
            "display": "flex",
            "flex": "1",
            "align-items": "center",
            "justify-content": "space-around",
            "line-height": "1",
            "font-size": "22px",
            "font-weight": "bold"
          }
        }
      ]
    }
  ]
}