[
  {
    "name": "pnp-list-formatting-exam-bundle-tracker",
    "reponame": "exam-bundle-tracker",
    "source": "pnp",
    "title": "Exam Bundle Tracker",
    "shortDescription": "This sample transforms your list into an Exam Bundle Tracker.",
    "url": "https://github.com/pnp/list-formatting/tree/master/view-samples/exam-bundle-tracker",
    "longDescription": [
      "This sample transforms your list into an Exam Bundle Tracker."
    ],
    "creationDateTime": "2023-07-14T00:00:00.000Z",
    "updateDateTime": "2023-07-14T00:00:00.000Z",
    "products": [
      "SharePoint",
      "Microsoft Lists"
    ],
    "metadata": [
      {
        "key": "LIST-SAMPLE-TYPE",
        "value": "View"
      },
      {
        "key": "SHAREPOINT-COMPATIBILITY",
        "value": "SharePoint Online"
      },
      {
        "key": "SAMPLE-CATEGORIES",
        "value": "Icons"
      },
      {
        "key": "LIST-COLUMN-TYPE",
        "value": ""
      },
      {
        "key": "FORMATTING-TOKENS",
        "value": "@group.fieldData, @group.count"
      },
      {
        "key": "FORMATTING-OPERATORS",
        "value": "indexOf, length, getUserImage"
      },
      {
        "key": "FORMATTING-ACTIONS",
        "value": "setValue, share, editProps"
      },
      {
        "key": "FORMATTING-FEATURES",
        "value": "hideSelection, hideColumnHeader, rowFormatter, groupProps, headerFormatter, forEach"
      },
      {
        "key": "CLASSES",
        "value": "ms-bgColor-grey, ms-bgColor-neutralLight, ms-bgColor-neutralQuaternary--hover, ms-bgColor-themeLighter, ms-bgColor-themeLight--hover, ms-fontColor-black, ms-fontColor-neutralPrimary, ms-fontColor-white--hover, ms-fontWeight-bold, ms-fontWeight-semibold, sp-css-backgroundColor-BgCoral, sp-css-backgroundColor-BgCornflowerBlue, sp-css-backgroundColor-BgCyan, sp-css-backgroundColor-BgCyan, sp-css-backgroundColor-BgCyan30--hover, sp-css-backgroundColor-BgDarkPink, sp-css-backgroundColor-BgDustRose, sp-css-backgroundColor-BgGold, sp-css-backgroundColor-BgLightBlue20, sp-css-backgroundColor-BgMintGreen, sp-css-backgroundColor-BgMintGreen, sp-css-backgroundColor-BgMintGreen30--hover, sp-css-backgroundColor-BgPeach, sp-css-backgroundColor-disabledBackground, sp-css-backgroundColor-neutralBackground, sp-css-borderLeftColor-CoralFont, sp-css-borderLeftColor-CornflowerBlueFont, sp-css-borderLeftColor-CyanFont, sp-css-borderLeftColor-DustRoseFont, sp-css-borderLeftColor-GoldFont, sp-css-borderLeftColor-MintGreenFont, sp-css-borderLeftColor-PeachFont, sp-css-borderRight-warningBorder, sp-css-borderTop-successBorder, sp-css-borderTop-warningBorder, sp-css-color-DustRoseFont, sp-css-color-MintGreenFont, sp-css-color-neutralFont, sp-css-color-WhiteText, sp-field-borderLeftBold, sp-field-borderLeftBold, sp-field-borderLeftSolid, sp-field-borderLeftSolid, sp-field-borderLeftSolid, sp-field-fontSizeSmall, sp-row-button, sp-row-buttonms-bgColor-grey, sp-row-card, sp-row-listPadding, sp-row-listPadding"
      }
    ],
    "thumbnails": [
      {
        "type": "image",
        "order": 100,
        "url": "https://raw.githubusercontent.com/pnp/List-Formatting/master/view-samples/exam-bundle-tracker/assets/screenshot.png",
        "alt": "screenshot"
      }
    ],
    "authors": [
      {
        "gitHubAccount": "z3019494",
        "pictureUrl": "https://github.com/z3019494.png",
        "name": "Hubert Lam"
      }
    ],
    "references": [
      {
        "name": "Use view formatting to customize SharePoint",
        "description": "You can use view formatting to customize how items in SharePoint lists and libraries are displayed. To do this, you construct a JSON object that describes the elements that are displayed when an item is loaded in a view and any styles to be applied to those elements.",
        "url": "https://docs.microsoft.com/sharepoint/dev/declarative-customization/view-formatting"
      }
    ]
  }
]