{
  "$schema": "https://developer.microsoft.com/json-schemas/sp/v2/row-formatting.schema.json",
  "hideColumnHeader": true,
  "hideSelection": true,
  "rowFormatter": {
    "elmType": "div",
    "style": {
      "display": "flex",
      "align-items": "flex-end",
      "justify-content": "flex-start",
      "flex-wrap": "wrap",
      "box-sizing": "border-box",
      "width": "1180px",
      "height": "460px"
    },
    "children": [
      {
        "elmType": "div",
        "inlineEditField": "[$Title]",
        "style": {
          "width": "686px",
          "box-sizing": "border-box",
          "display": "flex",
          "align-items": "flex-start",
          "justify-content": "center",
          "height": "30px",
          "position": "absolute",
          "top": "0",
          "left": "246px"
        },
        "children": [
          {
            "elmType": "div",
            "style": {
              "position": "relative",
              "display": "block",
              "top": "0px",
              "line-height": "20px",
              "box-sizing": "border-box",
              "white-space": "nowrap",
              "overflow": "hidden",
              "text-overflow": "ellipsis",
              "font-size": "22px",
              "font-weight": "bold",
              "color": "black",
              "cursor": "=if([$Author.email] == @me, 'pointer', '')"
            },
            "txtContent": "@currentField"
          }
        ]
      },
      {
        "elmType": "div",
        "inlineEditField": "[$SCALE]",
        "style": {
          "position": "absolute",
          "left": "1120px",
          "top": "2px",
          "height": "26px",
          "width": "26px",
          "box-sizing": "border-box",
          "display": "block",
          "visibility": "=if([$Author.email] == @me, 'visible', 'hidden')",
          "text-align": "center",
          "font-size": "16px",
          "font-weight": "bold",
          "cursor": "pointer"
        },
        "attributes": {
          "class": "sp-css-color-GrayText",
          "iconName": "SizeLegacy",
          "title": "='Scale: ' + [$SCALE.displayValue]"
        }
      },
      {
        "elmType": "div",
        "style": {
          "width": "1140px",
          "height": "312px",
          "box-sizing": "border-box",
          "display": "flex",
          "align-items": "flex-end",
          "justify-content": "flex-start",
          "margin-top": "30px",
          "border-bottom": "solid 1px lightgrey"
        },
        "children": [
          {
            "elmType": "div",
            "style": {
              "position": "relative",
              "display": "block",
              "flex-shrink": "1",
              "flex-grow": "1",
              "height": "312px",
              "max-width": "92px",
              "min-width": "92px",
              "top": "1px",
              "border-right": "solid 1px lightgrey",
              "background-color": "white"
            },
            "children": [
              {
                "elmType": "div",
                "style": {
                  "position": "relative",
                  "box-sizing": "border-box",
                  "display": "block",
                  "height": "10px",
                  "line-height": "10px",
                  "width": "auto",
                  "font-size": "15px",
                  "text-align": "right",
                  "padding-right": "4px",
                  "top": "-6px"
                },
                "txtContent": "[$SCALE.displayValue]"
              },
              {
                "elmType": "div",
                "style": {
                  "position": "relative",
                  "box-sizing": "border-box",
                  "display": "block",
                  "height": "10px",
                  "line-height": "10px",
                  "width": "auto",
                  "font-size": "15px",
                  "text-align": "right",
                  "padding-right": "4px",
                  "top": "140px"
                },
                "txtContent": "=[$SCALE]/2"
              },
              {
                "elmType": "div",
                "style": {
                  "position": "relative",
                  "box-sizing": "border-box",
                  "display": "block",
                  "height": "20px",
                  "width": "auto",
                  "font-size": "15px",
                  "text-align": "right",
                  "padding-right": "4px",
                  "top": "274px"
                },
                "txtContent": "0"
              }
            ]
          },
          {
            "elmType": "div",
            "style": {
              "box-sizing": "border-box",
              "position": "relative",
              "display": "block",
              "margin-right": "12px",
              "height": "0px",
              "width": "0px"
            },
            "children": [
              {
                "elmType": "div",
                "style": {
                  "position": "absolute",
                  "left": "-25px",
                  "bottom": "326px",
                  "width": "62px",
                  "height": "24px",
                  "display": "=if([$Author.email] == @me, 'flex', 'none')",
                  "align-items": "center",
                  "justify-content": "center"
                },
                "children": [
                  {
                    "elmType": "div",
                    "inlineEditField": "[$VALUE1_1]",
                    "style": {
                      "height": "24px",
                      "width": "28px",
                      "box-sizing": "border-box",
                      "display": "=if([$Author.email] == @me, 'flex', 'none')",
                      "align-items": "flex-end",
                      "justify-content": "center",
                      "padding-top": "0px",
                      "font-size": "20px",
                      "cursor": "pointer"
                    },
                    "attributes": {
                      "class": "sp-css-color-GrayText",
                      "iconName": "NumberField",
                      "title": "[$VALUE1_1]"
                    }
                  },
                  {
                    "elmType": "div",
                    "inlineEditField": "[$VALUE1_2]",
                    "style": {
                      "height": "24px",
                      "width": "28px",
                      "box-sizing": "border-box",
                      "display": "=if([$Author.email] == @me, 'flex', 'none')",
                      "align-items": "flex-end",
                      "justify-content": "center",
                      "font-size": "20px",
                      "cursor": "pointer"
                    },
                    "attributes": {
                      "class": "sp-css-color-GrayText",
                      "iconName": "NumberField",
                      "title": "[$VALUE1_2]"
                    }
                  }
                ]
              },
              {
                "elmType": "div",
                "style": {
                  "position": "absolute",
                  "z-index": "1",
                  "display": "=if([$VALUE1_1] =='', 'none', '')",
                  "box-sizing": "border-box",
                  "height": "12px",
                  "width": "12px",
                  "bottom": "=([$VALUE1_1]*312/[$SCALE]) - 6 +'px'",
                  "border-radius": "50%",
                  "background-color": "=if([$COLOR_1] =='', 'LightGrey', [$COLOR_1])"
                },
                "attributes": {
                  "title": "[$VALUE1_1.displayValue]"
                }
              },
              {
                "elmType": "div",
                "style": {
                  "position": "absolute",
                  "z-index": "0",
                  "display": "=if([$VALUE1_2] =='', 'none', '')",
                  "box-sizing": "border-box",
                  "height": "12px",
                  "width": "12px",
                  "bottom": "=([$VALUE1_2]*312/[$SCALE]) - 6 +'px'",
                  "border-radius": "50%",
                  "background-color": "=if([$COLOR_2] =='', 'LightGrey', [$COLOR_2])"
                },
                "attributes": {
                  "title": "[$VALUE1_2.displayValue]"
                }
              },
              {
                "elmType": "div",
                "inlineEditField": "[$LABEL1]",
                "style": {
                  "position": "absolute",
                  "top": "2px",
                  "left": "-42px",
                  "height": "26px",
                  "box-sizing": "border-box",
                  "display": "block",
                  "text-align": "center",
                  "padding-top": "0px",
                  "width": "94px",
                  "border-right": "solid 1px lightgrey",
                  "margin-right": "0px",
                  "font-size": "16px",
                  "font-weight": "500",
                  "cursor": "=if([$Author.email] == @me, 'pointer', '')",
                  "overflow": "hidden",
                  "white-space": "nowrap",
                  "text-overflow": "ellipsis"
                },
                "txtContent": "[$LABEL1]",
                "attributes": {
                  "class": "ms-bgColor-communicationTint40--hover sp-css-color-BlackText",
                  "title": "[$LABEL1]"
                }
              }
            ]
          },
          {
            "elmType": "svg",
            "style": {
              "height": "312px",
              "width": "82px"
            },
            "children": [
              {
                "elmType": "path",
                "style": {
                  "position": "absolute",
                  "z-index": "1",
                  "display": "=if([$VALUE1_1] =='' || [$VALUE2_1] =='', 'none', '')",
                  "stroke": "[$COLOR_1]"
                },
                "attributes": {
                  "d": "='M0,' + (312 - [$VALUE1_1]*312/[$SCALE]) + 'L82,'  + (312 - [$VALUE2_1]*312/[$SCALE])",
                  "fill": "none"
                }
              },
              {
                "elmType": "path",
                "style": {
                  "position": "absolute",
                  "z-index": "0",
                  "display": "=if([$VALUE1_2] =='' || [$VALUE2_2] =='', 'none', '')",
                  "stroke": "[$COLOR_2]"
                },
                "attributes": {
                  "d": "='M0,' + (312 - [$VALUE1_2]*312/[$SCALE]) + 'L82,'  + (312 - [$VALUE2_2]*312/[$SCALE])",
                  "fill": "none"
                }
              }
            ]
          },
          {
            "elmType": "div",
            "style": {
              "box-sizing": "border-box",
              "position": "relative",
              "display": "block",
              "margin-right": "12px",
              "height": "0px",
              "width": "0px"
            },
            "children": [
              {
                "elmType": "div",
                "style": {
                  "position": "absolute",
                  "left": "-25px",
                  "bottom": "326px",
                  "width": "62px",
                  "height": "24px",
                  "display": "=if([$Author.email] == @me, 'flex', 'none')",
                  "align-items": "center",
                  "justify-content": "center"
                },
                "children": [
                  {
                    "elmType": "div",
                    "inlineEditField": "[$VALUE2_1]",
                    "style": {
                      "height": "24px",
                      "width": "28px",
                      "box-sizing": "border-box",
                      "display": "=if([$Author.email] == @me, 'flex', 'none')",
                      "align-items": "flex-end",
                      "justify-content": "center",
                      "padding-top": "0px",
                      "font-size": "20px",
                      "cursor": "pointer"
                    },
                    "attributes": {
                      "class": "sp-css-color-GrayText",
                      "iconName": "NumberField",
                      "title": "[$VALUE2_1]"
                    }
                  },
                  {
                    "elmType": "div",
                    "inlineEditField": "[$VALUE2_2]",
                    "style": {
                      "height": "24px",
                      "width": "28px",
                      "box-sizing": "border-box",
                      "display": "=if([$Author.email] == @me, 'flex', 'none')",
                      "align-items": "flex-end",
                      "justify-content": "center",
                      "font-size": "20px",
                      "cursor": "pointer"
                    },
                    "attributes": {
                      "class": "sp-css-color-GrayText",
                      "iconName": "NumberField",
                      "title": "[$VALUE2_2]"
                    }
                  }
                ]
              },
              {
                "elmType": "div",
                "style": {
                  "position": "absolute",
                  "z-index": "1",
                  "display": "=if([$VALUE2_1] =='', 'none', '')",
                  "box-sizing": "border-box",
                  "height": "12px",
                  "width": "12px",
                  "bottom": "=([$VALUE2_1]*312/[$SCALE]) - 6 +'px'",
                  "border-radius": "50%",
                  "background-color": "=if([$COLOR_1] =='', 'LightGrey', [$COLOR_1])"
                },
                "attributes": {
                  "title": "[$VALUE2_1.displayValue]"
                }
              },
              {
                "elmType": "div",
                "style": {
                  "position": "absolute",
                  "z-index": "0",
                  "display": "=if([$VALUE2_2] =='', 'none', '')",
                  "box-sizing": "border-box",
                  "height": "12px",
                  "width": "12px",
                  "bottom": "=([$VALUE2_2]*312/[$SCALE]) - 6 +'px'",
                  "border-radius": "50%",
                  "background-color": "=if([$COLOR_2] =='', 'LightGrey', [$COLOR_2])"
                },
                "attributes": {
                  "title": "[$VALUE2_2.displayValue]"
                }
              },
              {
                "elmType": "div",
                "inlineEditField": "[$LABEL2]",
                "style": {
                  "position": "absolute",
                  "top": "2px",
                  "left": "-42px",
                  "height": "26px",
                  "box-sizing": "border-box",
                  "display": "block",
                  "text-align": "center",
                  "padding-top": "0px",
                  "width": "94px",
                  "border-right": "solid 1px lightgrey",
                  "margin-right": "0px",
                  "font-size": "16px",
                  "font-weight": "500",
                  "cursor": "=if([$Author.email] == @me, 'pointer', '')",
                  "overflow": "hidden",
                  "white-space": "nowrap",
                  "text-overflow": "ellipsis"
                },
                "txtContent": "[$LABEL2]",
                "attributes": {
                  "class": "ms-bgColor-communicationTint40--hover sp-css-color-BlackText",
                  "title": "[$LABEL2]"
                }
              }
            ]
          },
          {
            "elmType": "svg",
            "style": {
              "height": "312px",
              "width": "82px"
            },
            "children": [
              {
                "elmType": "path",
                "style": {
                  "position": "absolute",
                  "z-index": "1",
                  "display": "=if([$VALUE2_1] =='' || [$VALUE3_1] =='', 'none', '')",
                  "stroke": "[$COLOR_1]"
                },
                "attributes": {
                  "d": "='M0,' + (312 - [$VALUE2_1]*312/[$SCALE]) + 'L82,'  + (312 - [$VALUE3_1]*312/[$SCALE])",
                  "fill": "none"
                }
              },
              {
                "elmType": "path",
                "style": {
                  "position": "absolute",
                  "z-index": "0",
                  "display": "=if([$VALUE2_2] =='' || [$VALUE3_2] =='', 'none', '')",
                  "stroke": "[$COLOR_2]"
                },
                "attributes": {
                  "d": "='M0,' + (312 - [$VALUE2_2]*312/[$SCALE]) + 'L82,'  + (312 - [$VALUE3_2]*312/[$SCALE])",
                  "fill": "none"
                }
              }
            ]
          },
          {
            "elmType": "div",
            "style": {
              "box-sizing": "border-box",
              "position": "relative",
              "display": "block",
              "margin-right": "12px",
              "height": "0px",
              "width": "0px"
            },
            "children": [
              {
                "elmType": "div",
                "style": {
                  "position": "absolute",
                  "left": "-25px",
                  "bottom": "326px",
                  "width": "62px",
                  "height": "24px",
                  "display": "=if([$Author.email] == @me, 'flex', 'none')",
                  "align-items": "center",
                  "justify-content": "center"
                },
                "children": [
                  {
                    "elmType": "div",
                    "inlineEditField": "[$VALUE3_1]",
                    "style": {
                      "height": "24px",
                      "width": "28px",
                      "box-sizing": "border-box",
                      "display": "=if([$Author.email] == @me, 'flex', 'none')",
                      "align-items": "flex-end",
                      "justify-content": "center",
                      "padding-top": "0px",
                      "font-size": "20px",
                      "cursor": "pointer"
                    },
                    "attributes": {
                      "class": "sp-css-color-GrayText",
                      "iconName": "NumberField",
                      "title": "[$VALUE3_1]"
                    }
                  },
                  {
                    "elmType": "div",
                    "inlineEditField": "[$VALUE3_2]",
                    "style": {
                      "height": "24px",
                      "width": "28px",
                      "box-sizing": "border-box",
                      "display": "=if([$Author.email] == @me, 'flex', 'none')",
                      "align-items": "flex-end",
                      "justify-content": "center",
                      "font-size": "20px",
                      "cursor": "pointer"
                    },
                    "attributes": {
                      "class": "sp-css-color-GrayText",
                      "iconName": "NumberField",
                      "title": "[$VALUE3_2]"
                    }
                  }
                ]
              },
              {
                "elmType": "div",
                "style": {
                  "position": "absolute",
                  "z-index": "1",
                  "display": "=if([$VALUE3_1] =='', 'none', '')",
                  "box-sizing": "border-box",
                  "height": "12px",
                  "width": "12px",
                  "bottom": "=([$VALUE3_1]*312/[$SCALE]) - 6 +'px'",
                  "border-radius": "50%",
                  "background-color": "=if([$COLOR_1] =='', 'LightGrey', [$COLOR_1])"
                },
                "attributes": {
                  "title": "[$VALUE3_1.displayValue]"
                }
              },
              {
                "elmType": "div",
                "style": {
                  "position": "absolute",
                  "z-index": "0",
                  "display": "=if([$VALUE3_2] =='', 'none', '')",
                  "box-sizing": "border-box",
                  "height": "12px",
                  "width": "12px",
                  "bottom": "=([$VALUE3_2]*312/[$SCALE]) - 6 +'px'",
                  "border-radius": "50%",
                  "background-color": "=if([$COLOR_2] =='', 'LightGrey', [$COLOR_2])"
                },
                "attributes": {
                  "title": "[$VALUE3_2.displayValue]"
                }
              },
              {
                "elmType": "div",
                "inlineEditField": "[$LABEL3]",
                "style": {
                  "position": "absolute",
                  "top": "2px",
                  "left": "-42px",
                  "height": "26px",
                  "box-sizing": "border-box",
                  "display": "block",
                  "text-align": "center",
                  "padding-top": "0px",
                  "width": "94px",
                  "border-right": "solid 1px lightgrey",
                  "margin-right": "0px",
                  "font-size": "16px",
                  "font-weight": "500",
                  "cursor": "=if([$Author.email] == @me, 'pointer', '')",
                  "line-height": "",
                  "overflow": "hidden",
                  "white-space": "nowrap",
                  "text-overflow": "ellipsis"
                },
                "txtContent": "[$LABEL3]",
                "attributes": {
                  "class": "ms-bgColor-communicationTint40--hover sp-css-color-BlackText",
                  "title": "[$LABEL3]"
                }
              }
            ]
          },
          {
            "elmType": "svg",
            "style": {
              "height": "312px",
              "width": "82px"
            },
            "children": [
              {
                "elmType": "path",
                "style": {
                  "position": "absolute",
                  "z-index": "1",
                  "display": "=if([$VALUE3_1] =='' || [$VALUE4_1] =='', 'none', '')",
                  "stroke": "[$COLOR_1]"
                },
                "attributes": {
                  "d": "='M0,' + (312 - [$VALUE3_1]*312/[$SCALE]) + 'L82,'  + (312 - [$VALUE4_1]*312/[$SCALE])",
                  "fill": "none"
                }
              },
              {
                "elmType": "path",
                "style": {
                  "position": "absolute",
                  "z-index": "0",
                  "display": "=if([$VALUE3_2] =='' || [$VALUE4_2] =='', 'none', '')",
                  "stroke": "[$COLOR_2]"
                },
                "attributes": {
                  "d": "='M0,' + (312 - [$VALUE3_2]*312/[$SCALE]) + 'L82,'  + (312 - [$VALUE4_2]*312/[$SCALE])",
                  "fill": "none"
                }
              }
            ]
          },
          {
            "elmType": "div",
            "style": {
              "box-sizing": "border-box",
              "position": "relative",
              "display": "block",
              "margin-right": "12px",
              "height": "0px",
              "width": "0px"
            },
            "children": [
              {
                "elmType": "div",
                "style": {
                  "position": "absolute",
                  "left": "-25px",
                  "bottom": "326px",
                  "width": "62px",
                  "height": "24px",
                  "display": "=if([$Author.email] == @me, 'flex', 'none')",
                  "align-items": "center",
                  "justify-content": "center"
                },
                "children": [
                  {
                    "elmType": "div",
                    "inlineEditField": "[$VALUE4_1]",
                    "style": {
                      "height": "24px",
                      "width": "28px",
                      "box-sizing": "border-box",
                      "display": "=if([$Author.email] == @me, 'flex', 'none')",
                      "align-items": "flex-end",
                      "justify-content": "center",
                      "padding-top": "0px",
                      "font-size": "20px",
                      "cursor": "pointer"
                    },
                    "attributes": {
                      "class": "sp-css-color-GrayText",
                      "iconName": "NumberField",
                      "title": "[$VALUE4_1]"
                    }
                  },
                  {
                    "elmType": "div",
                    "inlineEditField": "[$VALUE4_2]",
                    "style": {
                      "height": "24px",
                      "width": "28px",
                      "box-sizing": "border-box",
                      "display": "=if([$Author.email] == @me, 'flex', 'none')",
                      "align-items": "flex-end",
                      "justify-content": "center",
                      "font-size": "20px",
                      "cursor": "pointer"
                    },
                    "attributes": {
                      "class": "sp-css-color-GrayText",
                      "iconName": "NumberField",
                      "title": "[$VALUE4_2]"
                    }
                  }
                ]
              },
              {
                "elmType": "div",
                "style": {
                  "position": "absolute",
                  "z-index": "1",
                  "display": "=if([$VALUE4_1] =='', 'none', '')",
                  "box-sizing": "border-box",
                  "height": "12px",
                  "width": "12px",
                  "bottom": "=([$VALUE4_1]*312/[$SCALE]) - 6 +'px'",
                  "border-radius": "50%",
                  "background-color": "=if([$COLOR_1] =='', 'LightGrey', [$COLOR_1])"
                },
                "attributes": {
                  "title": "[$VALUE4_1.displayValue]"
                }
              },
              {
                "elmType": "div",
                "style": {
                  "position": "absolute",
                  "z-index": "0",
                  "display": "=if([$VALUE4_2] =='', 'none', '')",
                  "box-sizing": "border-box",
                  "height": "12px",
                  "width": "12px",
                  "bottom": "=([$VALUE4_2]*312/[$SCALE]) - 6 +'px'",
                  "border-radius": "50%",
                  "background-color": "=if([$COLOR_2] =='', 'LightGrey', [$COLOR_2])"
                },
                "attributes": {
                  "title": "[$VALUE4_2.displayValue]"
                }
              },
              {
                "elmType": "div",
                "inlineEditField": "[$LABEL4]",
                "style": {
                  "position": "absolute",
                  "top": "2px",
                  "left": "-42px",
                  "height": "26px",
                  "box-sizing": "border-box",
                  "display": "block",
                  "text-align": "center",
                  "padding-top": "0px",
                  "width": "94px",
                  "border-right": "solid 1px lightgrey",
                  "margin-right": "0px",
                  "font-size": "16px",
                  "font-weight": "500",
                  "cursor": "=if([$Author.email] == @me, 'pointer', '')",
                  "line-height": "",
                  "overflow": "hidden",
                  "white-space": "nowrap",
                  "text-overflow": "ellipsis"
                },
                "txtContent": "[$LABEL4]",
                "attributes": {
                  "class": "ms-bgColor-communicationTint40--hover sp-css-color-BlackText",
                  "title": "[$LABEL4]"
                }
              }
            ]
          },
          {
            "elmType": "svg",
            "style": {
              "height": "312px",
              "width": "82px"
            },
            "children": [
              {
                "elmType": "path",
                "style": {
                  "position": "absolute",
                  "z-index": "1",
                  "display": "=if([$VALUE4_1] =='' || [$VALUE5_1] =='', 'none', '')",
                  "stroke": "[$COLOR_1]"
                },
                "attributes": {
                  "d": "='M0,' + (312 - [$VALUE4_1]*312/[$SCALE]) + 'L82,'  + (312 - [$VALUE5_1]*312/[$SCALE])",
                  "fill": "none"
                }
              },
              {
                "elmType": "path",
                "style": {
                  "position": "absolute",
                  "z-index": "0",
                  "display": "=if([$VALUE4_2] =='' || [$VALUE5_2] =='', 'none', '')",
                  "stroke": "[$COLOR_2]"
                },
                "attributes": {
                  "d": "='M0,' + (312 - [$VALUE4_2]*312/[$SCALE]) + 'L82,'  + (312 - [$VALUE5_2]*312/[$SCALE])",
                  "fill": "none"
                }
              }
            ]
          },
          {
            "elmType": "div",
            "style": {
              "box-sizing": "border-box",
              "position": "relative",
              "display": "block",
              "margin-right": "12px",
              "height": "0px",
              "width": "0px"
            },
            "children": [
              {
                "elmType": "div",
                "style": {
                  "position": "absolute",
                  "left": "-25px",
                  "bottom": "326px",
                  "width": "62px",
                  "height": "24px",
                  "display": "=if([$Author.email] == @me, 'flex', 'none')",
                  "align-items": "center",
                  "justify-content": "center"
                },
                "children": [
                  {
                    "elmType": "div",
                    "inlineEditField": "[$VALUE5_1]",
                    "style": {
                      "height": "24px",
                      "width": "28px",
                      "box-sizing": "border-box",
                      "display": "=if([$Author.email] == @me, 'flex', 'none')",
                      "align-items": "flex-end",
                      "justify-content": "center",
                      "padding-top": "0px",
                      "font-size": "20px",
                      "cursor": "pointer"
                    },
                    "attributes": {
                      "class": "sp-css-color-GrayText",
                      "iconName": "NumberField",
                      "title": "[$VALUE5_1]"
                    }
                  },
                  {
                    "elmType": "div",
                    "inlineEditField": "[$VALUE5_2]",
                    "style": {
                      "height": "24px",
                      "width": "28px",
                      "box-sizing": "border-box",
                      "display": "=if([$Author.email] == @me, 'flex', 'none')",
                      "align-items": "flex-end",
                      "justify-content": "center",
                      "font-size": "20px",
                      "cursor": "pointer"
                    },
                    "attributes": {
                      "class": "sp-css-color-GrayText",
                      "iconName": "NumberField",
                      "title": "[$VALUE5_2]"
                    }
                  }
                ]
              },
              {
                "elmType": "div",
                "style": {
                  "position": "absolute",
                  "z-index": "1",
                  "display": "=if([$VALUE5_1] =='', 'none', '')",
                  "box-sizing": "border-box",
                  "height": "12px",
                  "width": "12px",
                  "bottom": "=([$VALUE5_1]*312/[$SCALE]) - 6 +'px'",
                  "border-radius": "50%",
                  "background-color": "=if([$COLOR_1] =='', 'LightGrey', [$COLOR_1])"
                },
                "attributes": {
                  "title": "[$VALUE5_1.displayValue]"
                }
              },
              {
                "elmType": "div",
                "style": {
                  "position": "absolute",
                  "z-index": "0",
                  "display": "=if([$VALUE5_2] =='', 'none', '')",
                  "box-sizing": "border-box",
                  "height": "12px",
                  "width": "12px",
                  "bottom": "=([$VALUE5_2]*312/[$SCALE]) - 6 +'px'",
                  "border-radius": "50%",
                  "background-color": "=if([$COLOR_2] =='', 'LightGrey', [$COLOR_2])"
                },
                "attributes": {
                  "title": "[$VALUE5_2.displayValue]"
                }
              },
              {
                "elmType": "div",
                "inlineEditField": "[$LABEL5]",
                "style": {
                  "position": "absolute",
                  "top": "2px",
                  "left": "-42px",
                  "height": "26px",
                  "box-sizing": "border-box",
                  "display": "block",
                  "text-align": "center",
                  "padding-top": "0px",
                  "width": "94px",
                  "border-right": "solid 1px lightgrey",
                  "margin-right": "0px",
                  "font-size": "16px",
                  "font-weight": "500",
                  "cursor": "=if([$Author.email] == @me, 'pointer', '')",
                  "overflow": "hidden",
                  "white-space": "nowrap",
                  "text-overflow": "ellipsis"
                },
                "txtContent": "[$LABEL5]",
                "attributes": {
                  "class": "ms-bgColor-communicationTint40--hover sp-css-color-BlackText",
                  "title": "[$LABEL5]"
                }
              }
            ]
          },
          {
            "elmType": "svg",
            "style": {
              "height": "312px",
              "width": "82px"
            },
            "children": [
              {
                "elmType": "path",
                "style": {
                  "position": "absolute",
                  "z-index": "1",
                  "display": "=if([$VALUE5_1] =='' || [$VALUE6_1] =='', 'none', '')",
                  "stroke": "[$COLOR_1]"
                },
                "attributes": {
                  "d": "='M0,' + (312 - [$VALUE5_1]*312/[$SCALE]) + 'L82,'  + (312 - [$VALUE6_1]*312/[$SCALE])",
                  "fill": "none"
                }
              },
              {
                "elmType": "path",
                "style": {
                  "position": "absolute",
                  "z-index": "0",
                  "display": "=if([$VALUE5_2] =='' || [$VALUE6_2] =='', 'none', '')",
                  "stroke": "[$COLOR_2]"
                },
                "attributes": {
                  "d": "='M0,' + (312 - [$VALUE5_2]*312/[$SCALE]) + 'L82,'  + (312 - [$VALUE6_2]*312/[$SCALE])",
                  "fill": "none"
                }
              }
            ]
          },
          {
            "elmType": "div",
            "style": {
              "box-sizing": "border-box",
              "position": "relative",
              "display": "block",
              "margin-right": "12px",
              "height": "0px",
              "width": "0px"
            },
            "children": [
              {
                "elmType": "div",
                "style": {
                  "position": "absolute",
                  "left": "-25px",
                  "bottom": "326px",
                  "width": "62px",
                  "height": "24px",
                  "display": "=if([$Author.email] == @me, 'flex', 'none')",
                  "align-items": "center",
                  "justify-content": "center"
                },
                "children": [
                  {
                    "elmType": "div",
                    "inlineEditField": "[$VALUE6_1]",
                    "style": {
                      "height": "24px",
                      "width": "28px",
                      "box-sizing": "border-box",
                      "display": "=if([$Author.email] == @me, 'flex', 'none')",
                      "align-items": "flex-end",
                      "justify-content": "center",
                      "padding-top": "0px",
                      "font-size": "20px",
                      "cursor": "pointer"
                    },
                    "attributes": {
                      "class": "sp-css-color-GrayText",
                      "iconName": "NumberField",
                      "title": "[$VALUE6_1]"
                    }
                  },
                  {
                    "elmType": "div",
                    "inlineEditField": "[$VALUE6_2]",
                    "style": {
                      "height": "24px",
                      "width": "28px",
                      "box-sizing": "border-box",
                      "display": "=if([$Author.email] == @me, 'flex', 'none')",
                      "align-items": "flex-end",
                      "justify-content": "center",
                      "font-size": "20px",
                      "cursor": "pointer"
                    },
                    "attributes": {
                      "class": "sp-css-color-GrayText",
                      "iconName": "NumberField",
                      "title": "[$VALUE6_2]"
                    }
                  }
                ]
              },
              {
                "elmType": "div",
                "style": {
                  "position": "absolute",
                  "z-index": "1",
                  "display": "=if([$VALUE6_1] =='', 'none', '')",
                  "box-sizing": "border-box",
                  "height": "12px",
                  "width": "12px",
                  "bottom": "=([$VALUE6_1]*312/[$SCALE]) - 6 +'px'",
                  "border-radius": "50%",
                  "background-color": "=if([$COLOR_1] =='', 'LightGrey', [$COLOR_1])"
                },
                "attributes": {
                  "title": "[$VALUE6_1.displayValue]"
                }
              },
              {
                "elmType": "div",
                "style": {
                  "position": "absolute",
                  "z-index": "0",
                  "display": "=if([$VALUE6_2] =='', 'none', '')",
                  "box-sizing": "border-box",
                  "height": "12px",
                  "width": "12px",
                  "bottom": "=([$VALUE6_2]*312/[$SCALE]) - 6 +'px'",
                  "border-radius": "50%",
                  "background-color": "=if([$COLOR_2] =='', 'LightGrey', [$COLOR_2])"
                },
                "attributes": {
                  "title": "[$VALUE6_2.displayValue]"
                }
              },
              {
                "elmType": "div",
                "inlineEditField": "[$LABEL6]",
                "style": {
                  "position": "absolute",
                  "top": "2px",
                  "left": "-42px",
                  "height": "26px",
                  "box-sizing": "border-box",
                  "display": "block",
                  "text-align": "center",
                  "padding-top": "0px",
                  "width": "94px",
                  "border-right": "solid 1px lightgrey",
                  "margin-right": "0px",
                  "font-size": "16px",
                  "font-weight": "500",
                  "cursor": "=if([$Author.email] == @me, 'pointer', '')",
                  "overflow": "hidden",
                  "white-space": "nowrap",
                  "text-overflow": "ellipsis"
                },
                "txtContent": "[$LABEL6]",
                "attributes": {
                  "class": "ms-bgColor-communicationTint40--hover sp-css-color-BlackText",
                  "title": "[$LABEL6]"
                }
              }
            ]
          },
          {
            "elmType": "svg",
            "style": {
              "height": "312px",
              "width": "82px"
            },
            "children": [
              {
                "elmType": "path",
                "style": {
                  "position": "absolute",
                  "z-index": "1",
                  "display": "=if([$VALUE6_1] =='' || [$VALUE7_1] =='', 'none', '')",
                  "stroke": "[$COLOR_1]"
                },
                "attributes": {
                  "d": "='M0,' + (312 - [$VALUE6_1]*312/[$SCALE]) + 'L82,'  + (312 - [$VALUE7_1]*312/[$SCALE])",
                  "fill": "none"
                }
              },
              {
                "elmType": "path",
                "style": {
                  "position": "absolute",
                  "z-index": "0",
                  "display": "=if([$VALUE6_2] =='' || [$VALUE7_2] =='', 'none', '')",
                  "stroke": "[$COLOR_2]"
                },
                "attributes": {
                  "d": "='M0,' + (312 - [$VALUE6_2]*312/[$SCALE]) + 'L82,'  + (312 - [$VALUE7_2]*312/[$SCALE])",
                  "fill": "none"
                }
              }
            ]
          },
          {
            "elmType": "div",
            "style": {
              "box-sizing": "border-box",
              "position": "relative",
              "display": "block",
              "margin-right": "12px",
              "height": "0px",
              "width": "0px"
            },
            "children": [
              {
                "elmType": "div",
                "style": {
                  "position": "absolute",
                  "left": "-25px",
                  "bottom": "326px",
                  "width": "62px",
                  "height": "24px",
                  "display": "=if([$Author.email] == @me, 'flex', 'none')",
                  "align-items": "center",
                  "justify-content": "center"
                },
                "children": [
                  {
                    "elmType": "div",
                    "inlineEditField": "[$VALUE7_1]",
                    "style": {
                      "height": "24px",
                      "width": "28px",
                      "box-sizing": "border-box",
                      "display": "=if([$Author.email] == @me, 'flex', 'none')",
                      "align-items": "flex-end",
                      "justify-content": "center",
                      "padding-top": "0px",
                      "font-size": "20px",
                      "cursor": "pointer"
                    },
                    "attributes": {
                      "class": "sp-css-color-GrayText",
                      "iconName": "NumberField",
                      "title": "[$VALUE7_1]"
                    }
                  },
                  {
                    "elmType": "div",
                    "inlineEditField": "[$VALUE7_2]",
                    "style": {
                      "height": "24px",
                      "width": "28px",
                      "box-sizing": "border-box",
                      "display": "=if([$Author.email] == @me, 'flex', 'none')",
                      "align-items": "flex-end",
                      "justify-content": "center",
                      "font-size": "20px",
                      "cursor": "pointer"
                    },
                    "attributes": {
                      "class": "sp-css-color-GrayText",
                      "iconName": "NumberField",
                      "title": "[$VALUE7_2]"
                    }
                  }
                ]
              },
              {
                "elmType": "div",
                "style": {
                  "position": "absolute",
                  "z-index": "1",
                  "display": "=if([$VALUE7_1] =='', 'none', '')",
                  "box-sizing": "border-box",
                  "height": "12px",
                  "width": "12px",
                  "bottom": "=([$VALUE7_1]*312/[$SCALE]) - 6 +'px'",
                  "border-radius": "50%",
                  "background-color": "=if([$COLOR_1] =='', 'LightGrey', [$COLOR_1])"
                },
                "attributes": {
                  "title": "[$VALUE7_1.displayValue]"
                }
              },
              {
                "elmType": "div",
                "style": {
                  "position": "absolute",
                  "z-index": "0",
                  "display": "=if([$VALUE7_2] =='', 'none', '')",
                  "box-sizing": "border-box",
                  "height": "12px",
                  "width": "12px",
                  "bottom": "=([$VALUE7_2]*312/[$SCALE]) - 6 +'px'",
                  "border-radius": "50%",
                  "background-color": "=if([$COLOR_2] =='', 'LightGrey', [$COLOR_2])"
                },
                "attributes": {
                  "title": "[$VALUE7_2.displayValue]"
                }
              },
              {
                "elmType": "div",
                "inlineEditField": "[$LABEL7]",
                "style": {
                  "position": "absolute",
                  "top": "2px",
                  "left": "-42px",
                  "height": "26px",
                  "box-sizing": "border-box",
                  "display": "block",
                  "text-align": "center",
                  "padding-top": "0px",
                  "width": "94px",
                  "border-right": "solid 1px lightgrey",
                  "margin-right": "0px",
                  "font-size": "16px",
                  "font-weight": "500",
                  "cursor": "=if([$Author.email] == @me, 'pointer', '')",
                  "overflow": "hidden",
                  "white-space": "nowrap",
                  "text-overflow": "ellipsis"
                },
                "txtContent": "[$LABEL7]",
                "attributes": {
                  "class": "ms-bgColor-communicationTint40--hover sp-css-color-BlackText",
                  "title": "[$LABEL7]"
                }
              }
            ]
          },
          {
            "elmType": "svg",
            "style": {
              "height": "312px",
              "width": "82px"
            },
            "children": [
              {
                "elmType": "path",
                "style": {
                  "position": "absolute",
                  "z-index": "1",
                  "display": "=if([$VALUE7_1] =='' || [$VALUE8_1] =='', 'none', '')",
                  "stroke": "[$COLOR_1]"
                },
                "attributes": {
                  "d": "='M0,' + (312 - [$VALUE7_1]*312/[$SCALE]) + 'L82,'  + (312 - [$VALUE8_1]*312/[$SCALE])",
                  "fill": "none"
                }
              },
              {
                "elmType": "path",
                "style": {
                  "position": "absolute",
                  "z-index": "0",
                  "display": "=if([$VALUE7_2] =='' || [$VALUE8_2] =='', 'none', '')",
                  "stroke": "[$COLOR_2]"
                },
                "attributes": {
                  "d": "='M0,' + (312 - [$VALUE7_2]*312/[$SCALE]) + 'L82,'  + (312 - [$VALUE8_2]*312/[$SCALE])",
                  "fill": "none"
                }
              }
            ]
          },
          {
            "elmType": "div",
            "style": {
              "box-sizing": "border-box",
              "position": "relative",
              "display": "block",
              "margin-right": "12px",
              "height": "0px",
              "width": "0px"
            },
            "children": [
              {
                "elmType": "div",
                "style": {
                  "position": "absolute",
                  "left": "-25px",
                  "bottom": "326px",
                  "width": "62px",
                  "height": "24px",
                  "display": "=if([$Author.email] == @me, 'flex', 'none')",
                  "align-items": "center",
                  "justify-content": "center"
                },
                "children": [
                  {
                    "elmType": "div",
                    "inlineEditField": "[$VALUE8_1]",
                    "style": {
                      "height": "24px",
                      "width": "28px",
                      "box-sizing": "border-box",
                      "display": "=if([$Author.email] == @me, 'flex', 'none')",
                      "align-items": "flex-end",
                      "justify-content": "center",
                      "padding-top": "0px",
                      "font-size": "20px",
                      "cursor": "pointer"
                    },
                    "attributes": {
                      "class": "sp-css-color-GrayText",
                      "iconName": "NumberField",
                      "title": "[$VALUE8_1]"
                    }
                  },
                  {
                    "elmType": "div",
                    "inlineEditField": "[$VALUE8_2]",
                    "style": {
                      "height": "24px",
                      "width": "28px",
                      "box-sizing": "border-box",
                      "display": "=if([$Author.email] == @me, 'flex', 'none')",
                      "align-items": "flex-end",
                      "justify-content": "center",
                      "font-size": "20px",
                      "cursor": "pointer"
                    },
                    "attributes": {
                      "class": "sp-css-color-GrayText",
                      "iconName": "NumberField",
                      "title": "[$VALUE8_2]"
                    }
                  }
                ]
              },
              {
                "elmType": "div",
                "style": {
                  "position": "absolute",
                  "z-index": "1",
                  "display": "=if([$VALUE8_1] =='', 'none', '')",
                  "box-sizing": "border-box",
                  "height": "12px",
                  "width": "12px",
                  "bottom": "=([$VALUE8_1]*312/[$SCALE]) - 6 +'px'",
                  "border-radius": "50%",
                  "background-color": "=if([$COLOR_1] =='', 'LightGrey', [$COLOR_1])"
                },
                "attributes": {
                  "title": "[$VALUE8_1.displayValue]"
                }
              },
              {
                "elmType": "div",
                "style": {
                  "position": "absolute",
                  "z-index": "0",
                  "display": "=if([$VALUE8_2] =='', 'none', '')",
                  "box-sizing": "border-box",
                  "height": "12px",
                  "width": "12px",
                  "bottom": "=([$VALUE8_2]*312/[$SCALE]) - 6 +'px'",
                  "border-radius": "50%",
                  "background-color": "=if([$COLOR_2] =='', 'LightGrey', [$COLOR_2])"
                },
                "attributes": {
                  "title": "[$VALUE8_2.displayValue]"
                }
              },
              {
                "elmType": "div",
                "inlineEditField": "[$LABEL8]",
                "style": {
                  "position": "absolute",
                  "top": "2px",
                  "left": "-42px",
                  "height": "26px",
                  "box-sizing": "border-box",
                  "display": "block",
                  "text-align": "center",
                  "padding-top": "0px",
                  "width": "94px",
                  "border-right": "solid 1px lightgrey",
                  "margin-right": "0px",
                  "font-size": "16px",
                  "font-weight": "500",
                  "cursor": "=if([$Author.email] == @me, 'pointer', '')",
                  "overflow": "hidden",
                  "white-space": "nowrap",
                  "text-overflow": "ellipsis"
                },
                "txtContent": "[$LABEL8]",
                "attributes": {
                  "class": "ms-bgColor-communicationTint40--hover sp-css-color-BlackText",
                  "title": "[$LABEL8]"
                }
              }
            ]
          },
          {
            "elmType": "svg",
            "style": {
              "height": "312px",
              "width": "82px"
            },
            "children": [
              {
                "elmType": "path",
                "style": {
                  "position": "absolute",
                  "z-index": "1",
                  "display": "=if([$VALUE8_1] =='' || [$VALUE9_1] =='', 'none', '')",
                  "stroke": "[$COLOR_1]"
                },
                "attributes": {
                  "d": "='M0,' + (312 - [$VALUE8_1]*312/[$SCALE]) + 'L82,'  + (312 - [$VALUE9_1]*312/[$SCALE])",
                  "fill": "none"
                }
              },
              {
                "elmType": "path",
                "style": {
                  "position": "absolute",
                  "z-index": "0",
                  "display": "=if([$VALUE8_2] =='' || [$VALUE9_2] =='', 'none', '')",
                  "stroke": "[$COLOR_2]"
                },
                "attributes": {
                  "d": "='M0,' + (312 - [$VALUE8_2]*312/[$SCALE]) + 'L82,'  + (312 - [$VALUE9_2]*312/[$SCALE])",
                  "fill": "none"
                }
              }
            ]
          },
          {
            "elmType": "div",
            "style": {
              "box-sizing": "border-box",
              "position": "relative",
              "display": "block",
              "margin-right": "12px",
              "height": "0px",
              "width": "0px"
            },
            "children": [
              {
                "elmType": "div",
                "style": {
                  "position": "absolute",
                  "left": "-25px",
                  "bottom": "326px",
                  "width": "62px",
                  "height": "24px",
                  "display": "=if([$Author.email] == @me, 'flex', 'none')",
                  "align-items": "center",
                  "justify-content": "center"
                },
                "children": [
                  {
                    "elmType": "div",
                    "inlineEditField": "[$VALUE9_1]",
                    "style": {
                      "height": "24px",
                      "width": "28px",
                      "box-sizing": "border-box",
                      "display": "=if([$Author.email] == @me, 'flex', 'none')",
                      "align-items": "flex-end",
                      "justify-content": "center",
                      "padding-top": "0px",
                      "font-size": "20px",
                      "cursor": "pointer"
                    },
                    "attributes": {
                      "class": "sp-css-color-GrayText",
                      "iconName": "NumberField",
                      "title": "[$VALUE9_1]"
                    }
                  },
                  {
                    "elmType": "div",
                    "inlineEditField": "[$VALUE9_2]",
                    "style": {
                      "height": "24px",
                      "width": "28px",
                      "box-sizing": "border-box",
                      "display": "=if([$Author.email] == @me, 'flex', 'none')",
                      "align-items": "flex-end",
                      "justify-content": "center",
                      "font-size": "20px",
                      "cursor": "pointer"
                    },
                    "attributes": {
                      "class": "sp-css-color-GrayText",
                      "iconName": "NumberField",
                      "title": "[$VALUE9_2]"
                    }
                  }
                ]
              },
              {
                "elmType": "div",
                "style": {
                  "position": "absolute",
                  "z-index": "1",
                  "display": "=if([$VALUE9_1] =='', 'none', '')",
                  "box-sizing": "border-box",
                  "height": "12px",
                  "width": "12px",
                  "bottom": "=([$VALUE9_1]*312/[$SCALE]) - 6 +'px'",
                  "border-radius": "50%",
                  "background-color": "=if([$COLOR_1] =='', 'LightGrey', [$COLOR_1])"
                },
                "attributes": {
                  "title": "[$VALUE9_1.displayValue]"
                }
              },
              {
                "elmType": "div",
                "style": {
                  "position": "absolute",
                  "z-index": "0",
                  "display": "=if([$VALUE9_2] =='', 'none', '')",
                  "box-sizing": "border-box",
                  "height": "12px",
                  "width": "12px",
                  "bottom": "=([$VALUE9_2]*312/[$SCALE]) - 6 +'px'",
                  "border-radius": "50%",
                  "background-color": "=if([$COLOR_2] =='', 'LightGrey', [$COLOR_2])"
                },
                "attributes": {
                  "title": "[$VALUE9_2.displayValue]"
                }
              },
              {
                "elmType": "div",
                "inlineEditField": "[$LABEL9]",
                "style": {
                  "position": "absolute",
                  "top": "2px",
                  "left": "-42px",
                  "height": "26px",
                  "box-sizing": "border-box",
                  "display": "block",
                  "text-align": "center",
                  "padding-top": "0px",
                  "align-items": "",
                  "width": "94px",
                  "border-right": "solid 1px lightgrey",
                  "margin-right": "0px",
                  "font-size": "16px",
                  "font-weight": "500",
                  "cursor": "=if([$Author.email] == @me, 'pointer', '')",
                  "overflow": "hidden",
                  "white-space": "nowrap",
                  "text-overflow": "ellipsis"
                },
                "txtContent": "[$LABEL9]",
                "attributes": {
                  "class": "ms-bgColor-communicationTint40--hover sp-css-color-BlackText",
                  "title": "[$LABEL9]"
                }
              }
            ]
          },
          {
            "elmType": "svg",
            "style": {
              "height": "312px",
              "width": "82px"
            },
            "children": [
              {
                "elmType": "path",
                "style": {
                  "position": "absolute",
                  "z-index": "1",
                  "display": "=if([$VALUE9_1] =='' || [$VALUE10_1] =='', 'none', '')",
                  "stroke": "[$COLOR_1]"
                },
                "attributes": {
                  "d": "='M0,' + (312 - [$VALUE9_1]*312/[$SCALE]) + 'L82,'  + (312 - [$VALUE10_1]*312/[$SCALE])",
                  "fill": "none"
                }
              },
              {
                "elmType": "path",
                "style": {
                  "position": "absolute",
                  "z-index": "0",
                  "display": "=if([$VALUE9_2] =='' || [$VALUE10_2] =='', 'none', '')",
                  "stroke": "[$COLOR_2]"
                },
                "attributes": {
                  "d": "='M0,' + (312 - [$VALUE9_2]*312/[$SCALE]) + 'L82,'  + (312 - [$VALUE10_2]*312/[$SCALE])",
                  "fill": "none"
                }
              }
            ]
          },
          {
            "elmType": "div",
            "style": {
              "box-sizing": "border-box",
              "position": "relative",
              "display": "block",
              "margin-right": "12px",
              "height": "0px",
              "width": "0px"
            },
            "children": [
              {
                "elmType": "div",
                "style": {
                  "position": "absolute",
                  "left": "-25px",
                  "bottom": "326px",
                  "width": "62px",
                  "height": "24px",
                  "display": "=if([$Author.email] == @me, 'flex', 'none')",
                  "align-items": "center",
                  "justify-content": "center"
                },
                "children": [
                  {
                    "elmType": "div",
                    "inlineEditField": "[$VALUE10_1]",
                    "style": {
                      "height": "24px",
                      "width": "28px",
                      "box-sizing": "border-box",
                      "display": "=if([$Author.email] == @me, 'flex', 'none')",
                      "align-items": "flex-end",
                      "justify-content": "center",
                      "padding-top": "0px",
                      "font-size": "20px",
                      "cursor": "pointer"
                    },
                    "attributes": {
                      "class": "sp-css-color-GrayText",
                      "iconName": "NumberField",
                      "title": "[$VALUE10_1]"
                    }
                  },
                  {
                    "elmType": "div",
                    "inlineEditField": "[$VALUE10_2]",
                    "style": {
                      "height": "24px",
                      "width": "28px",
                      "box-sizing": "border-box",
                      "display": "=if([$Author.email] == @me, 'flex', 'none')",
                      "align-items": "flex-end",
                      "justify-content": "center",
                      "font-size": "20px",
                      "cursor": "pointer"
                    },
                    "attributes": {
                      "class": "sp-css-color-GrayText",
                      "iconName": "NumberField",
                      "title": "[$VALUE10_2]"
                    }
                  }
                ]
              },
              {
                "elmType": "div",
                "style": {
                  "position": "absolute",
                  "z-index": "1",
                  "display": "=if([$VALUE10_1] =='', 'none', '')",
                  "box-sizing": "border-box",
                  "height": "12px",
                  "width": "12px",
                  "bottom": "=([$VALUE10_1]*312/[$SCALE]) - 6 +'px'",
                  "border-radius": "50%",
                  "background-color": "=if([$COLOR_1] =='', 'LightGrey', [$COLOR_1])"
                },
                "attributes": {
                  "title": "[$VALUE10_1.displayValue]"
                }
              },
              {
                "elmType": "div",
                "style": {
                  "position": "absolute",
                  "z-index": "0",
                  "display": "=if([$VALUE10_2] =='', 'none', '')",
                  "box-sizing": "border-box",
                  "height": "12px",
                  "width": "12px",
                  "bottom": "=([$VALUE10_2]*312/[$SCALE]) - 6 +'px'",
                  "border-radius": "50%",
                  "background-color": "=if([$COLOR_2] =='', 'LightGrey', [$COLOR_2])"
                },
                "attributes": {
                  "title": "[$VALUE10_2.displayValue]"
                }
              },
              {
                "elmType": "div",
                "inlineEditField": "[$LABEL10]",
                "style": {
                  "position": "absolute",
                  "top": "2px",
                  "left": "-42px",
                  "height": "26px",
                  "box-sizing": "border-box",
                  "display": "block",
                  "text-align": "center",
                  "padding-top": "0px",
                  "width": "94px",
                  "border-right": "solid 1px lightgrey",
                  "margin-right": "0px",
                  "font-size": "16px",
                  "font-weight": "500",
                  "cursor": "=if([$Author.email] == @me, 'pointer', '')",
                  "overflow": "hidden",
                  "white-space": "nowrap",
                  "text-overflow": "ellipsis"
                },
                "txtContent": "[$LABEL10]",
                "attributes": {
                  "class": "ms-bgColor-communicationTint40--hover sp-css-color-BlackText",
                  "title": "[$LABEL10]"
                }
              }
            ]
          },
          {
            "elmType": "svg",
            "style": {
              "height": "312px",
              "width": "82px"
            },
            "children": [
              {
                "elmType": "path",
                "style": {
                  "position": "absolute",
                  "z-index": "1",
                  "display": "=if([$VALUE10_1] =='' || [$VALUE11_1] =='', 'none', '')",
                  "stroke": "[$COLOR_1]"
                },
                "attributes": {
                  "d": "='M0,' + (312 - [$VALUE10_1]*312/[$SCALE]) + 'L82,'  + (312 - [$VALUE11_1]*312/[$SCALE])",
                  "fill": "none"
                }
              },
              {
                "elmType": "path",
                "style": {
                  "position": "absolute",
                  "z-index": "0",
                  "display": "=if([$VALUE10_2] =='' || [$VALUE11_2] =='', 'none', '')",
                  "stroke": "[$COLOR_2]"
                },
                "attributes": {
                  "d": "='M0,' + (312 - [$VALUE10_2]*312/[$SCALE]) + 'L82,'  + (312 - [$VALUE11_2]*312/[$SCALE])",
                  "fill": "none"
                }
              }
            ]
          },
          {
            "elmType": "div",
            "style": {
              "box-sizing": "border-box",
              "position": "relative",
              "display": "block",
              "margin-right": "12px",
              "height": "0px",
              "width": "0px"
            },
            "children": [
              {
                "elmType": "div",
                "style": {
                  "position": "absolute",
                  "left": "-25px",
                  "bottom": "326px",
                  "width": "62px",
                  "height": "24px",
                  "display": "=if([$Author.email] == @me, 'flex', 'none')",
                  "align-items": "center",
                  "justify-content": "center"
                },
                "children": [
                  {
                    "elmType": "div",
                    "inlineEditField": "[$VALUE11_1]",
                    "style": {
                      "height": "24px",
                      "width": "28px",
                      "box-sizing": "border-box",
                      "display": "=if([$Author.email] == @me, 'flex', 'none')",
                      "align-items": "flex-end",
                      "justify-content": "center",
                      "padding-top": "0px",
                      "font-size": "20px",
                      "cursor": "pointer"
                    },
                    "attributes": {
                      "class": "sp-css-color-GrayText",
                      "iconName": "NumberField",
                      "title": "[$VALUE11_1]"
                    }
                  },
                  {
                    "elmType": "div",
                    "inlineEditField": "[$VALUE11_2]",
                    "style": {
                      "height": "24px",
                      "width": "28px",
                      "box-sizing": "border-box",
                      "display": "=if([$Author.email] == @me, 'flex', 'none')",
                      "align-items": "flex-end",
                      "justify-content": "center",
                      "font-size": "20px",
                      "cursor": "pointer"
                    },
                    "attributes": {
                      "class": "sp-css-color-GrayText",
                      "iconName": "NumberField",
                      "title": "[$VALUE11_2]"
                    }
                  }
                ]
              },
              {
                "elmType": "div",
                "style": {
                  "position": "absolute",
                  "z-index": "1",
                  "display": "=if([$VALUE11_1] =='', 'none', '')",
                  "box-sizing": "border-box",
                  "height": "12px",
                  "width": "12px",
                  "bottom": "=([$VALUE11_1]*312/[$SCALE]) - 6 +'px'",
                  "border-radius": "50%",
                  "background-color": "=if([$COLOR_1] =='', 'LightGrey', [$COLOR_1])"
                },
                "attributes": {
                  "title": "[$VALUE11_1.displayValue]"
                }
              },
              {
                "elmType": "div",
                "style": {
                  "position": "absolute",
                  "z-index": "0",
                  "display": "=if([$VALUE11_2] =='', 'none', '')",
                  "box-sizing": "border-box",
                  "height": "12px",
                  "width": "12px",
                  "bottom": "=([$VALUE11_2]*312/[$SCALE]) - 6 +'px'",
                  "border-radius": "50%",
                  "background-color": "=if([$COLOR_2] =='', 'LightGrey', [$COLOR_2])"
                },
                "attributes": {
                  "title": "[$VALUE11_2.displayValue]"
                }
              },
              {
                "elmType": "div",
                "inlineEditField": "[$LABEL11]",
                "style": {
                  "position": "absolute",
                  "top": "2px",
                  "left": "-42px",
                  "height": "26px",
                  "box-sizing": "border-box",
                  "display": "block",
                  "text-align": "center",
                  "padding-top": "0px",
                  "align-items": "",
                  "width": "94px",
                  "border-right": "solid 1px lightgrey",
                  "margin-right": "0px",
                  "font-size": "16px",
                  "font-weight": "500",
                  "cursor": "=if([$Author.email] == @me, 'pointer', '')",
                  "overflow": "hidden",
                  "white-space": "nowrap",
                  "text-overflow": "ellipsis"
                },
                "txtContent": "[$LABEL11]",
                "attributes": {
                  "class": "ms-bgColor-communicationTint40--hover sp-css-color-BlackText",
                  "title": "[$LABEL11]"
                }
              }
            ]
          },
          {
            "elmType": "svg",
            "style": {
              "height": "312px",
              "width": "82px"
            },
            "children": [
              {
                "elmType": "path",
                "style": {
                  "position": "absolute",
                  "z-index": "1",
                  "display": "=if([$VALUE11_1] =='' || [$VALUE12_1] =='', 'none', '')",
                  "stroke": "[$COLOR_1]"
                },
                "attributes": {
                  "d": "='M0,' + (312 - [$VALUE11_1]*312/[$SCALE]) + 'L82,'  + (312 - [$VALUE12_1]*312/[$SCALE])",
                  "fill": "none"
                }
              },
              {
                "elmType": "path",
                "style": {
                  "position": "absolute",
                  "z-index": "0",
                  "display": "=if([$VALUE11_2] =='' || [$VALUE12_2] =='', 'none', '')",
                  "stroke": "[$COLOR_2]"
                },
                "attributes": {
                  "d": "='M0,' + (312 - [$VALUE11_2]*312/[$SCALE]) + 'L82,'  + (312 - [$VALUE12_2]*312/[$SCALE])",
                  "fill": "none"
                }
              }
            ]
          },
          {
            "elmType": "div",
            "style": {
              "box-sizing": "border-box",
              "position": "relative",
              "display": "block",
              "margin-right": "12px",
              "height": "0px",
              "width": "0px"
            },
            "children": [
              {
                "elmType": "div",
                "style": {
                  "position": "absolute",
                  "left": "-25px",
                  "bottom": "326px",
                  "width": "62px",
                  "height": "24px",
                  "display": "=if([$Author.email] == @me, 'flex', 'none')",
                  "align-items": "center",
                  "justify-content": "center"
                },
                "children": [
                  {
                    "elmType": "div",
                    "inlineEditField": "[$VALUE12_1]",
                    "style": {
                      "height": "24px",
                      "width": "28px",
                      "box-sizing": "border-box",
                      "display": "=if([$Author.email] == @me, 'flex', 'none')",
                      "align-items": "flex-end",
                      "justify-content": "center",
                      "padding-top": "0px",
                      "font-size": "20px",
                      "cursor": "pointer"
                    },
                    "attributes": {
                      "class": "sp-css-color-GrayText",
                      "iconName": "NumberField",
                      "title": "[$VALUE12_1]"
                    }
                  },
                  {
                    "elmType": "div",
                    "inlineEditField": "[$VALUE12_2]",
                    "style": {
                      "height": "24px",
                      "width": "28px",
                      "box-sizing": "border-box",
                      "display": "=if([$Author.email] == @me, 'flex', 'none')",
                      "align-items": "flex-end",
                      "justify-content": "center",
                      "font-size": "20px",
                      "cursor": "pointer"
                    },
                    "attributes": {
                      "class": "sp-css-color-GrayText",
                      "iconName": "NumberField",
                      "title": "[$VALUE12_2]"
                    }
                  }
                ]
              },
              {
                "elmType": "div",
                "style": {
                  "position": "absolute",
                  "z-index": "1",
                  "display": "=if([$VALUE12_1] =='', 'none', '')",
                  "box-sizing": "border-box",
                  "height": "12px",
                  "width": "12px",
                  "bottom": "=([$VALUE12_1]*312/[$SCALE]) - 6 +'px'",
                  "border-radius": "50%",
                  "background-color": "=if([$COLOR_1] =='', 'LightGrey', [$COLOR_1])"
                },
                "attributes": {
                  "title": "[$VALUE12_1.displayValue]"
                }
              },
              {
                "elmType": "div",
                "style": {
                  "position": "absolute",
                  "z-index": "0",
                  "display": "=if([$VALUE12_2] =='', 'none', '')",
                  "box-sizing": "border-box",
                  "height": "12px",
                  "width": "12px",
                  "bottom": "=([$VALUE12_2]*312/[$SCALE]) - 6 +'px'",
                  "border-radius": "50%",
                  "background-color": "=if([$COLOR_2] =='', 'LightGrey', [$COLOR_2])"
                },
                "attributes": {
                  "title": "[$VALUE12_2.displayValue]"
                }
              },
              {
                "elmType": "div",
                "inlineEditField": "[$LABEL12]",
                "style": {
                  "position": "absolute",
                  "top": "2px",
                  "left": "-42px",
                  "height": "26px",
                  "box-sizing": "border-box",
                  "display": "block",
                  "text-align": "center",
                  "padding-top": "0px",
                  "width": "94px",
                  "margin-right": "0px",
                  "font-size": "16px",
                  "font-weight": "500",
                  "cursor": "=if([$Author.email] == @me, 'pointer', '')",
                  "overflow": "hidden",
                  "white-space": "nowrap",
                  "text-overflow": "ellipsis"
                },
                "txtContent": "[$LABEL12]",
                "attributes": {
                  "class": "ms-bgColor-communicationTint40--hover sp-css-color-BlackText",
                  "title": "[$LABEL12]"
                }
              }
            ]
          }
        ]
      },
      {
        "elmType": "div",
        "style": {
          "width": "686px",
          "box-sizing": "border-box",
          "display": "flex",
          "align-items": "center",
          "justify-content": "center",
          "height": "30px",
          "position": "relative",
          "left": "246px"
        },
        "children": [
          {
            "elmType": "div",
            "style": {
              "display": "flex"
            },
            "children": [
              {
                "elmType": "div",
                "inlineEditField": "[$COLOR_1]",
                "style": {
                  "box-sizing": "border-box",
                  "width": "20px",
                  "height": "20px",
                  "border-radius": "50%",
                  "background-color": "=if([$COLOR_1] =='', 'LightGrey', [$COLOR_1])",
                  "margin-right": "6px",
                  "cursor": "=if([$Author.email] == @me, 'pointer', '')"
                }
              },
              {
                "elmType": "div",
                "inlineEditField": "[$CATEGORY_1]",
                "style": {
                  "box-sizing": "border-box",
                  "max-width": "180px",
                  "height": "26px",
                  "margin-right": "14px",
                  "font-size": "16px",
                  "font-weight": "500",
                  "color": "=if([$CATEGORY_1] =='', '#bdbfbe', 'Black')",
                  "line-height": "20px",
                  "white-space": "nowrap",
                  "overflow": "hidden",
                  "text-overflow": "ellipsis",
                  "cursor": "=if([$Author.email] == @me, 'pointer', '')"
                },
                "attributes": {
                  "title": "[$CATEGORY_1]"
                },
                "txtContent": "=if([$CATEGORY_1] =='', 'Category 1', [$CATEGORY_1])"
              }
            ]
          },
          {
            "elmType": "div",
            "style": {
              "display": "flex"
            },
            "children": [
              {
                "elmType": "div",
                "inlineEditField": "[$COLOR_2]",
                "style": {
                  "box-sizing": "border-box",
                  "width": "20px",
                  "height": "20px",
                  "border-radius": "50%",
                  "background-color": "=if([$COLOR_2] =='', 'LightGrey', [$COLOR_2])",
                  "margin-right": "6px",
                  "cursor": "=if([$Author.email] == @me, 'pointer', '')"
                }
              },
              {
                "elmType": "div",
                "inlineEditField": "[$CATEGORY_2]",
                "style": {
                  "box-sizing": "border-box",
                  "max-width": "180px",
                  "height": "26px",
                  "font-size": "16px",
                  "font-weight": "500",
                  "color": "=if([$CATEGORY_2] =='', '#bdbfbe', 'Black')",
                  "line-height": "20px",
                  "white-space": "nowrap",
                  "overflow": "hidden",
                  "text-overflow": "ellipsis",
                  "cursor": "=if([$Author.email] == @me, 'pointer', '')"
                },
                "attributes": {
                  "title": "[$CATEGORY_2]"
                },
                "txtContent": "=if([$CATEGORY_2] =='', 'Category 1', [$CATEGORY_2])"
              }
            ]
          }
        ]
      }
    ]
  }
}
